qekgr/__init__.py
qekgr/cli.py
quantum_entangled_knowledge_graphs-1.1.0.dist-info/licenses/LICENSE
quantum_entangled_knowledge_graphs-1.1.0.dist-info/METADATA
quantum_entangled_knowledge_graphs-1.1.0.dist-info/WHEEL
quantum_entangled_knowledge_graphs-1.1.0.dist-info/entry_points.txt
quantum_entangled_knowledge_graphs-1.1.0.dist-info/top_level.txt
quantum_entangled_knowledge_graphs-1.1.0.dist-info/RECORD
