Metadata-Version: 2.4
Name: quantum-entangled-knowledge-graphs
Version: 1.1.0
Summary: World's first open-source library for quantum-enhanced knowledge graph reasoning using entanglement principles
Home-page: https://github.com/krish567366/quantum-entangled-knowledge-graphs
Author: Krishna Bajpai
Author-email: Krishna Bajpai <bajpaikrishna715@gmail.com>
Maintainer-email: Krishna Bajpai <bajpaikrishna715@gmail.com>
License: Commercial
Project-URL: Homepage, https://github.com/krish567366/quantum-entangled-knowledge-graphs
Project-URL: Documentation, https://krish567366.github.io/quantum-entangled-knowledge-graphs/
Project-URL: Repository, https://github.com/krish567366/quantum-entangled-knowledge-graphs
Project-URL: Bug Tracker, https://github.com/krish567366/quantum-entangled-knowledge-graphs/issues
Keywords: quantum computing,knowledge graphs,quantum entanglement,graph neural networks,quantum machine learning,semantic reasoning,artificial intelligence
Classifier: Development Status :: 4 - Beta
Classifier: Intended Audience :: Developers
Classifier: Intended Audience :: Science/Research
Classifier: License :: Other/Proprietary License
Classifier: Operating System :: OS Independent
Classifier: Programming Language :: Python :: 3
Classifier: Programming Language :: Python :: 3.8
Classifier: Programming Language :: Python :: 3.9
Classifier: Programming Language :: Python :: 3.10
Classifier: Programming Language :: Python :: 3.11
Classifier: Topic :: Scientific/Engineering :: Artificial Intelligence
Classifier: Topic :: Scientific/Engineering :: Physics
Classifier: Topic :: Software Development :: Libraries :: Python Modules
Requires-Python: >=3.8
License-File: LICENSE
Requires-Dist: numpy>=1.21.0
Requires-Dist: scipy>=1.7.0
Requires-Dist: networkx>=2.6.0
Requires-Dist: matplotlib>=3.4.0
Requires-Dist: plotly>=5.0.0
Requires-Dist: pandas>=1.3.0
Requires-Dist: scikit-learn>=1.0.0
Requires-Dist: seaborn>=0.11.0
Requires-Dist: quantummeta-license>=1.0.0
Provides-Extra: quantum
Requires-Dist: pennylane>=0.28.0; extra == "quantum"
Requires-Dist: qiskit>=0.39.0; extra == "quantum"
Provides-Extra: visualization
Requires-Dist: pyvis>=0.3.0; extra == "visualization"
Requires-Dist: graphviz>=0.20.0; extra == "visualization"
Provides-Extra: dev
Requires-Dist: pytest>=6.0.0; extra == "dev"
Requires-Dist: pytest-cov>=3.0.0; extra == "dev"
Requires-Dist: black>=22.0.0; extra == "dev"
Requires-Dist: flake8>=4.0.0; extra == "dev"
Requires-Dist: mypy>=0.950; extra == "dev"
Requires-Dist: mkdocs>=1.4.0; extra == "dev"
Requires-Dist: mkdocs-material>=8.0.0; extra == "dev"
Requires-Dist: mkdocstrings[python]>=0.19.0; extra == "dev"
Provides-Extra: examples
Requires-Dist: jupyter>=1.0.0; extra == "examples"
Requires-Dist: streamlit>=1.15.0; extra == "examples"
Requires-Dist: gradio>=3.0.0; extra == "examples"
Dynamic: author
Dynamic: home-page
Dynamic: license-file
Dynamic: requires-python
